<?xml version="1.0"?>
<ArrayOfSequence xmlns:xsd="http://www.w3.org/2001/XMLSchema" xmlns:xsi="http://www.w3.org/2001/XMLSchema-instance">
  <Sequence>
    <Classes>
      <string />
    </Classes>
    <SourcePath>
      <Point>
        <X>203</X>
        <Y>155</Y>
      </Point>
      <Point>
        <X>203</X>
        <Y>156</Y>
      </Point>
      <Point>
        <X>203</X>
        <Y>156</Y>
      </Point>
      <Point>
        <X>203</X>
        <Y>158</Y>
      </Point>
      <Point>
        <X>203</X>
        <Y>160</Y>
      </Point>
      <Point>
        <X>203</X>
        <Y>162</Y>
      </Point>
      <Point>
        <X>203</X>
        <Y>162</Y>
      </Point>
      <Point>
        <X>204</X>
        <Y>164</Y>
      </Point>
      <Point>
        <X>204</X>
        <Y>167</Y>
      </Point>
      <Point>
        <X>204</X>
        <Y>170</Y>
      </Point>
      <Point>
        <X>204</X>
        <Y>173</Y>
      </Point>
      <Point>
        <X>204</X>
        <Y>176</Y>
      </Point>
      <Point>
        <X>204</X>
        <Y>178</Y>
      </Point>
      <Point>
        <X>204</X>
        <Y>180</Y>
      </Point>
      <Point>
        <X>204</X>
        <Y>184</Y>
      </Point>
      <Point>
        <X>204</X>
        <Y>188</Y>
      </Point>
      <Point>
        <X>204</X>
        <Y>192</Y>
      </Point>
      <Point>
        <X>204</X>
        <Y>195</Y>
      </Point>
      <Point>
        <X>204</X>
        <Y>199</Y>
      </Point>
      <Point>
        <X>204</X>
        <Y>202</Y>
      </Point>
      <Point>
        <X>204</X>
        <Y>204</Y>
      </Point>
      <Point>
        <X>204</X>
        <Y>207</Y>
      </Point>
      <Point>
        <X>204</X>
        <Y>211</Y>
      </Point>
      <Point>
        <X>204</X>
        <Y>215</Y>
      </Point>
      <Point>
        <X>204</X>
        <Y>217</Y>
      </Point>
      <Point>
        <X>204</X>
        <Y>220</Y>
      </Point>
      <Point>
        <X>204</X>
        <Y>223</Y>
      </Point>
      <Point>
        <X>204</X>
        <Y>226</Y>
      </Point>
      <Point>
        <X>204</X>
        <Y>229</Y>
      </Point>
      <Point>
        <X>203</X>
        <Y>233</Y>
      </Point>
      <Point>
        <X>203</X>
        <Y>237</Y>
      </Point>
      <Point>
        <X>202</X>
        <Y>240</Y>
      </Point>
      <Point>
        <X>202</X>
        <Y>243</Y>
      </Point>
      <Point>
        <X>202</X>
        <Y>245</Y>
      </Point>
      <Point>
        <X>202</X>
        <Y>246</Y>
      </Point>
      <Point>
        <X>202</X>
        <Y>248</Y>
      </Point>
      <Point>
        <X>202</X>
        <Y>248</Y>
      </Point>
      <Point>
        <X>202</X>
        <Y>249</Y>
      </Point>
      <Point>
        <X>201</X>
        <Y>250</Y>
      </Point>
      <Point>
        <X>201</X>
        <Y>251</Y>
      </Point>
      <Point>
        <X>201</X>
        <Y>252</Y>
      </Point>
      <Point>
        <X>201</X>
        <Y>252</Y>
      </Point>
      <Point>
        <X>201</X>
        <Y>253</Y>
      </Point>
      <Point>
        <X>201</X>
        <Y>254</Y>
      </Point>
      <Point>
        <X>200</X>
        <Y>255</Y>
      </Point>
      <Point>
        <X>200</X>
        <Y>255</Y>
      </Point>
      <Point>
        <X>200</X>
        <Y>257</Y>
      </Point>
      <Point>
        <X>200</X>
        <Y>257</Y>
      </Point>
      <Point>
        <X>199</X>
        <Y>258</Y>
      </Point>
      <Point>
        <X>199</X>
        <Y>261</Y>
      </Point>
      <Point>
        <X>199</X>
        <Y>265</Y>
      </Point>
      <Point>
        <X>198</X>
        <Y>266</Y>
      </Point>
      <Point>
        <X>198</X>
        <Y>267</Y>
      </Point>
      <Point>
        <X>197</X>
        <Y>269</Y>
      </Point>
      <Point>
        <X>197</X>
        <Y>271</Y>
      </Point>
      <Point>
        <X>197</X>
        <Y>271</Y>
      </Point>
      <Point>
        <X>198</X>
        <Y>273</Y>
      </Point>
      <Point>
        <X>198</X>
        <Y>273</Y>
      </Point>
      <Point>
        <X>199</X>
        <Y>273</Y>
      </Point>
      <Point>
        <X>200</X>
        <Y>273</Y>
      </Point>
      <Point>
        <X>203</X>
        <Y>274</Y>
      </Point>
      <Point>
        <X>206</X>
        <Y>275</Y>
      </Point>
      <Point>
        <X>207</X>
        <Y>275</Y>
      </Point>
      <Point>
        <X>209</X>
        <Y>275</Y>
      </Point>
      <Point>
        <X>213</X>
        <Y>275</Y>
      </Point>
      <Point>
        <X>215</X>
        <Y>275</Y>
      </Point>
      <Point>
        <X>218</X>
        <Y>276</Y>
      </Point>
      <Point>
        <X>222</X>
        <Y>278</Y>
      </Point>
      <Point>
        <X>225</X>
        <Y>278</Y>
      </Point>
      <Point>
        <X>230</X>
        <Y>279</Y>
      </Point>
      <Point>
        <X>231</X>
        <Y>279</Y>
      </Point>
      <Point>
        <X>234</X>
        <Y>279</Y>
      </Point>
      <Point>
        <X>238</X>
        <Y>280</Y>
      </Point>
      <Point>
        <X>242</X>
        <Y>280</Y>
      </Point>
      <Point>
        <X>246</X>
        <Y>280</Y>
      </Point>
      <Point>
        <X>251</X>
        <Y>280</Y>
      </Point>
      <Point>
        <X>256</X>
        <Y>280</Y>
      </Point>
      <Point>
        <X>259</X>
        <Y>280</Y>
      </Point>
      <Point>
        <X>263</X>
        <Y>280</Y>
      </Point>
      <Point>
        <X>265</X>
        <Y>280</Y>
      </Point>
      <Point>
        <X>268</X>
        <Y>280</Y>
      </Point>
      <Point>
        <X>271</X>
        <Y>280</Y>
      </Point>
      <Point>
        <X>276</X>
        <Y>280</Y>
      </Point>
      <Point>
        <X>279</X>
        <Y>280</Y>
      </Point>
      <Point>
        <X>283</X>
        <Y>280</Y>
      </Point>
      <Point>
        <X>286</X>
        <Y>280</Y>
      </Point>
      <Point>
        <X>289</X>
        <Y>280</Y>
      </Point>
      <Point>
        <X>292</X>
        <Y>280</Y>
      </Point>
      <Point>
        <X>294</X>
        <Y>280</Y>
      </Point>
      <Point>
        <X>297</X>
        <Y>280</Y>
      </Point>
      <Point>
        <X>298</X>
        <Y>280</Y>
      </Point>
      <Point>
        <X>299</X>
        <Y>280</Y>
      </Point>
      <Point>
        <X>301</X>
        <Y>280</Y>
      </Point>
      <Point>
        <X>304</X>
        <Y>280</Y>
      </Point>
      <Point>
        <X>307</X>
        <Y>280</Y>
      </Point>
      <Point>
        <X>309</X>
        <Y>280</Y>
      </Point>
      <Point>
        <X>311</X>
        <Y>280</Y>
      </Point>
      <Point>
        <X>312</X>
        <Y>280</Y>
      </Point>
      <Point>
        <X>313</X>
        <Y>280</Y>
      </Point>
      <Point>
        <X>314</X>
        <Y>280</Y>
      </Point>
      <Point>
        <X>315</X>
        <Y>280</Y>
      </Point>
      <Point>
        <X>316</X>
        <Y>280</Y>
      </Point>
      <Point>
        <X>315</X>
        <Y>280</Y>
      </Point>
      <Point>
        <X>316</X>
        <Y>280</Y>
      </Point>
      <Point>
        <X>317</X>
        <Y>280</Y>
      </Point>
      <Point>
        <X>316</X>
        <Y>280</Y>
      </Point>
      <Point>
        <X>317</X>
        <Y>280</Y>
      </Point>
      <Point>
        <X>318</X>
        <Y>280</Y>
      </Point>
      <Point>
        <X>318</X>
        <Y>280</Y>
      </Point>
      <Point>
        <X>320</X>
        <Y>280</Y>
      </Point>
      <Point>
        <X>321</X>
        <Y>280</Y>
      </Point>
      <Point>
        <X>321</X>
        <Y>280</Y>
      </Point>
      <Point>
        <X>322</X>
        <Y>280</Y>
      </Point>
      <Point>
        <X>323</X>
        <Y>280</Y>
      </Point>
      <Point>
        <X>322</X>
        <Y>280</Y>
      </Point>
    </SourcePath>
    <Output>0</Output>
    <RecognizedAs>-1</RecognizedAs>
  </Sequence>
  <Sequence>
    <Classes>
      <string />
    </Classes>
    <SourcePath>
      <Point>
        <X>150</X>
        <Y>121</Y>
      </Point>
      <Point>
        <X>150</X>
        <Y>122</Y>
      </Point>
      <Point>
        <X>150</X>
        <Y>126</Y>
      </Point>
      <Point>
        <X>150</X>
        <Y>128</Y>
      </Point>
      <Point>
        <X>150</X>
        <Y>130</Y>
      </Point>
      <Point>
        <X>150</X>
        <Y>132</Y>
      </Point>
      <Point>
        <X>150</X>
        <Y>134</Y>
      </Point>
      <Point>
        <X>151</X>
        <Y>136</Y>
      </Point>
      <Point>
        <X>151</X>
        <Y>136</Y>
      </Point>
      <Point>
        <X>151</X>
        <Y>140</Y>
      </Point>
      <Point>
        <X>151</X>
        <Y>140</Y>
      </Point>
      <Point>
        <X>151</X>
        <Y>142</Y>
      </Point>
      <Point>
        <X>151</X>
        <Y>145</Y>
      </Point>
      <Point>
        <X>151</X>
        <Y>147</Y>
      </Point>
      <Point>
        <X>151</X>
        <Y>147</Y>
      </Point>
      <Point>
        <X>151</X>
        <Y>151</Y>
      </Point>
      <Point>
        <X>151</X>
        <Y>151</Y>
      </Point>
      <Point>
        <X>151</X>
        <Y>152</Y>
      </Point>
      <Point>
        <X>151</X>
        <Y>152</Y>
      </Point>
      <Point>
        <X>151</X>
        <Y>153</Y>
      </Point>
      <Point>
        <X>151</X>
        <Y>155</Y>
      </Point>
      <Point>
        <X>152</X>
        <Y>159</Y>
      </Point>
      <Point>
        <X>152</X>
        <Y>160</Y>
      </Point>
      <Point>
        <X>152</X>
        <Y>161</Y>
      </Point>
      <Point>
        <X>152</X>
        <Y>161</Y>
      </Point>
      <Point>
        <X>152</X>
        <Y>162</Y>
      </Point>
      <Point>
        <X>152</X>
        <Y>163</Y>
      </Point>
      <Point>
        <X>152</X>
        <Y>163</Y>
      </Point>
      <Point>
        <X>152</X>
        <Y>167</Y>
      </Point>
      <Point>
        <X>152</X>
        <Y>168</Y>
      </Point>
      <Point>
        <X>152</X>
        <Y>168</Y>
      </Point>
      <Point>
        <X>152</X>
        <Y>171</Y>
      </Point>
      <Point>
        <X>152</X>
        <Y>172</Y>
      </Point>
      <Point>
        <X>152</X>
        <Y>173</Y>
      </Point>
      <Point>
        <X>152</X>
        <Y>174</Y>
      </Point>
      <Point>
        <X>152</X>
        <Y>175</Y>
      </Point>
      <Point>
        <X>152</X>
        <Y>178</Y>
      </Point>
      <Point>
        <X>150</X>
        <Y>180</Y>
      </Point>
      <Point>
        <X>150</X>
        <Y>183</Y>
      </Point>
      <Point>
        <X>150</X>
        <Y>185</Y>
      </Point>
      <Point>
        <X>150</X>
        <Y>188</Y>
      </Point>
      <Point>
        <X>150</X>
        <Y>190</Y>
      </Point>
      <Point>
        <X>150</X>
        <Y>193</Y>
      </Point>
      <Point>
        <X>149</X>
        <Y>196</Y>
      </Point>
      <Point>
        <X>149</X>
        <Y>199</Y>
      </Point>
      <Point>
        <X>148</X>
        <Y>202</Y>
      </Point>
      <Point>
        <X>147</X>
        <Y>203</Y>
      </Point>
      <Point>
        <X>147</X>
        <Y>205</Y>
      </Point>
      <Point>
        <X>147</X>
        <Y>208</Y>
      </Point>
      <Point>
        <X>147</X>
        <Y>211</Y>
      </Point>
      <Point>
        <X>147</X>
        <Y>212</Y>
      </Point>
      <Point>
        <X>147</X>
        <Y>213</Y>
      </Point>
      <Point>
        <X>147</X>
        <Y>214</Y>
      </Point>
      <Point>
        <X>147</X>
        <Y>216</Y>
      </Point>
      <Point>
        <X>147</X>
        <Y>216</Y>
      </Point>
      <Point>
        <X>147</X>
        <Y>217</Y>
      </Point>
      <Point>
        <X>148</X>
        <Y>216</Y>
      </Point>
      <Point>
        <X>147</X>
        <Y>218</Y>
      </Point>
      <Point>
        <X>147</X>
        <Y>219</Y>
      </Point>
      <Point>
        <X>147</X>
        <Y>220</Y>
      </Point>
      <Point>
        <X>148</X>
        <Y>220</Y>
      </Point>
      <Point>
        <X>147</X>
        <Y>222</Y>
      </Point>
      <Point>
        <X>147</X>
        <Y>223</Y>
      </Point>
      <Point>
        <X>147</X>
        <Y>224</Y>
      </Point>
      <Point>
        <X>147</X>
        <Y>225</Y>
      </Point>
      <Point>
        <X>147</X>
        <Y>225</Y>
      </Point>
      <Point>
        <X>148</X>
        <Y>225</Y>
      </Point>
      <Point>
        <X>147</X>
        <Y>227</Y>
      </Point>
      <Point>
        <X>147</X>
        <Y>228</Y>
      </Point>
      <Point>
        <X>147</X>
        <Y>229</Y>
      </Point>
      <Point>
        <X>148</X>
        <Y>228</Y>
      </Point>
      <Point>
        <X>147</X>
        <Y>229</Y>
      </Point>
      <Point>
        <X>147</X>
        <Y>230</Y>
      </Point>
      <Point>
        <X>147</X>
        <Y>230</Y>
      </Point>
      <Point>
        <X>148</X>
        <Y>230</Y>
      </Point>
      <Point>
        <X>147</X>
        <Y>231</Y>
      </Point>
      <Point>
        <X>148</X>
        <Y>230</Y>
      </Point>
      <Point>
        <X>147</X>
        <Y>231</Y>
      </Point>
      <Point>
        <X>148</X>
        <Y>231</Y>
      </Point>
      <Point>
        <X>147</X>
        <Y>233</Y>
      </Point>
      <Point>
        <X>147</X>
        <Y>234</Y>
      </Point>
      <Point>
        <X>147</X>
        <Y>234</Y>
      </Point>
      <Point>
        <X>147</X>
        <Y>235</Y>
      </Point>
      <Point>
        <X>147</X>
        <Y>236</Y>
      </Point>
      <Point>
        <X>147</X>
        <Y>237</Y>
      </Point>
      <Point>
        <X>147</X>
        <Y>237</Y>
      </Point>
      <Point>
        <X>148</X>
        <Y>237</Y>
      </Point>
      <Point>
        <X>147</X>
        <Y>239</Y>
      </Point>
      <Point>
        <X>147</X>
        <Y>240</Y>
      </Point>
      <Point>
        <X>147</X>
        <Y>241</Y>
      </Point>
      <Point>
        <X>147</X>
        <Y>242</Y>
      </Point>
      <Point>
        <X>147</X>
        <Y>244</Y>
      </Point>
      <Point>
        <X>147</X>
        <Y>244</Y>
      </Point>
      <Point>
        <X>147</X>
        <Y>245</Y>
      </Point>
      <Point>
        <X>148</X>
        <Y>247</Y>
      </Point>
      <Point>
        <X>149</X>
        <Y>247</Y>
      </Point>
      <Point>
        <X>148</X>
        <Y>247</Y>
      </Point>
      <Point>
        <X>151</X>
        <Y>248</Y>
      </Point>
      <Point>
        <X>154</X>
        <Y>249</Y>
      </Point>
      <Point>
        <X>156</X>
        <Y>249</Y>
      </Point>
      <Point>
        <X>161</X>
        <Y>249</Y>
      </Point>
      <Point>
        <X>165</X>
        <Y>250</Y>
      </Point>
      <Point>
        <X>167</X>
        <Y>250</Y>
      </Point>
      <Point>
        <X>171</X>
        <Y>250</Y>
      </Point>
      <Point>
        <X>179</X>
        <Y>250</Y>
      </Point>
      <Point>
        <X>187</X>
        <Y>251</Y>
      </Point>
      <Point>
        <X>197</X>
        <Y>251</Y>
      </Point>
      <Point>
        <X>207</X>
        <Y>251</Y>
      </Point>
      <Point>
        <X>218</X>
        <Y>253</Y>
      </Point>
      <Point>
        <X>255</X>
        <Y>257</Y>
      </Point>
      <Point>
        <X>262</X>
        <Y>258</Y>
      </Point>
      <Point>
        <X>269</X>
        <Y>258</Y>
      </Point>
      <Point>
        <X>274</X>
        <Y>258</Y>
      </Point>
      <Point>
        <X>280</X>
        <Y>258</Y>
      </Point>
      <Point>
        <X>285</X>
        <Y>258</Y>
      </Point>
      <Point>
        <X>290</X>
        <Y>258</Y>
      </Point>
      <Point>
        <X>296</X>
        <Y>258</Y>
      </Point>
      <Point>
        <X>303</X>
        <Y>258</Y>
      </Point>
      <Point>
        <X>308</X>
        <Y>258</Y>
      </Point>
      <Point>
        <X>315</X>
        <Y>257</Y>
      </Point>
      <Point>
        <X>319</X>
        <Y>257</Y>
      </Point>
      <Point>
        <X>324</X>
        <Y>256</Y>
      </Point>
      <Point>
        <X>328</X>
        <Y>255</Y>
      </Point>
      <Point>
        <X>332</X>
        <Y>254</Y>
      </Point>
      <Point>
        <X>335</X>
        <Y>253</Y>
      </Point>
      <Point>
        <X>338</X>
        <Y>253</Y>
      </Point>
      <Point>
        <X>342</X>
        <Y>252</Y>
      </Point>
      <Point>
        <X>345</X>
        <Y>252</Y>
      </Point>
      <Point>
        <X>348</X>
        <Y>252</Y>
      </Point>
      <Point>
        <X>348</X>
        <Y>252</Y>
      </Point>
      <Point>
        <X>349</X>
        <Y>252</Y>
      </Point>
      <Point>
        <X>350</X>
        <Y>252</Y>
      </Point>
    </SourcePath>
    <Output>0</Output>
    <RecognizedAs>-1</RecognizedAs>
  </Sequence>
  <Sequence>
    <Classes>
      <string />
    </Classes>
    <SourcePath>
      <Point>
        <X>151</X>
        <Y>125</Y>
      </Point>
      <Point>
        <X>150</X>
        <Y>125</Y>
      </Point>
      <Point>
        <X>151</X>
        <Y>126</Y>
      </Point>
      <Point>
        <X>151</X>
        <Y>127</Y>
      </Point>
      <Point>
        <X>151</X>
        <Y>128</Y>
      </Point>
      <Point>
        <X>151</X>
        <Y>131</Y>
      </Point>
      <Point>
        <X>150</X>
        <Y>136</Y>
      </Point>
      <Point>
        <X>149</X>
        <Y>138</Y>
      </Point>
      <Point>
        <X>148</X>
        <Y>142</Y>
      </Point>
      <Point>
        <X>148</X>
        <Y>147</Y>
      </Point>
      <Point>
        <X>147</X>
        <Y>154</Y>
      </Point>
      <Point>
        <X>146</X>
        <Y>162</Y>
      </Point>
      <Point>
        <X>146</X>
        <Y>170</Y>
      </Point>
      <Point>
        <X>146</X>
        <Y>177</Y>
      </Point>
      <Point>
        <X>146</X>
        <Y>183</Y>
      </Point>
      <Point>
        <X>146</X>
        <Y>189</Y>
      </Point>
      <Point>
        <X>146</X>
        <Y>195</Y>
      </Point>
      <Point>
        <X>146</X>
        <Y>201</Y>
      </Point>
      <Point>
        <X>146</X>
        <Y>207</Y>
      </Point>
      <Point>
        <X>147</X>
        <Y>212</Y>
      </Point>
      <Point>
        <X>147</X>
        <Y>218</Y>
      </Point>
      <Point>
        <X>147</X>
        <Y>223</Y>
      </Point>
      <Point>
        <X>148</X>
        <Y>228</Y>
      </Point>
      <Point>
        <X>149</X>
        <Y>233</Y>
      </Point>
      <Point>
        <X>150</X>
        <Y>238</Y>
      </Point>
      <Point>
        <X>150</X>
        <Y>242</Y>
      </Point>
      <Point>
        <X>150</X>
        <Y>246</Y>
      </Point>
      <Point>
        <X>150</X>
        <Y>250</Y>
      </Point>
      <Point>
        <X>151</X>
        <Y>254</Y>
      </Point>
      <Point>
        <X>152</X>
        <Y>257</Y>
      </Point>
      <Point>
        <X>152</X>
        <Y>260</Y>
      </Point>
      <Point>
        <X>152</X>
        <Y>263</Y>
      </Point>
      <Point>
        <X>152</X>
        <Y>266</Y>
      </Point>
      <Point>
        <X>152</X>
        <Y>270</Y>
      </Point>
      <Point>
        <X>153</X>
        <Y>273</Y>
      </Point>
      <Point>
        <X>153</X>
        <Y>276</Y>
      </Point>
      <Point>
        <X>154</X>
        <Y>280</Y>
      </Point>
      <Point>
        <X>155</X>
        <Y>282</Y>
      </Point>
      <Point>
        <X>155</X>
        <Y>285</Y>
      </Point>
      <Point>
        <X>155</X>
        <Y>286</Y>
      </Point>
      <Point>
        <X>155</X>
        <Y>287</Y>
      </Point>
      <Point>
        <X>155</X>
        <Y>290</Y>
      </Point>
      <Point>
        <X>155</X>
        <Y>291</Y>
      </Point>
      <Point>
        <X>155</X>
        <Y>291</Y>
      </Point>
      <Point>
        <X>156</X>
        <Y>292</Y>
      </Point>
      <Point>
        <X>159</X>
        <Y>293</Y>
      </Point>
      <Point>
        <X>162</X>
        <Y>293</Y>
      </Point>
      <Point>
        <X>168</X>
        <Y>293</Y>
      </Point>
      <Point>
        <X>176</X>
        <Y>293</Y>
      </Point>
      <Point>
        <X>187</X>
        <Y>293</Y>
      </Point>
      <Point>
        <X>198</X>
        <Y>293</Y>
      </Point>
      <Point>
        <X>213</X>
        <Y>293</Y>
      </Point>
      <Point>
        <X>229</X>
        <Y>293</Y>
      </Point>
      <Point>
        <X>248</X>
        <Y>293</Y>
      </Point>
      <Point>
        <X>268</X>
        <Y>293</Y>
      </Point>
      <Point>
        <X>287</X>
        <Y>293</Y>
      </Point>
      <Point>
        <X>303</X>
        <Y>293</Y>
      </Point>
      <Point>
        <X>318</X>
        <Y>293</Y>
      </Point>
      <Point>
        <X>331</X>
        <Y>293</Y>
      </Point>
      <Point>
        <X>342</X>
        <Y>293</Y>
      </Point>
      <Point>
        <X>351</X>
        <Y>293</Y>
      </Point>
      <Point>
        <X>358</X>
        <Y>293</Y>
      </Point>
      <Point>
        <X>362</X>
        <Y>293</Y>
      </Point>
      <Point>
        <X>365</X>
        <Y>293</Y>
      </Point>
      <Point>
        <X>367</X>
        <Y>293</Y>
      </Point>
      <Point>
        <X>368</X>
        <Y>293</Y>
      </Point>
      <Point>
        <X>369</X>
        <Y>293</Y>
      </Point>
      <Point>
        <X>371</X>
        <Y>293</Y>
      </Point>
      <Point>
        <X>371</X>
        <Y>293</Y>
      </Point>
      <Point>
        <X>373</X>
        <Y>293</Y>
      </Point>
      <Point>
        <X>374</X>
        <Y>293</Y>
      </Point>
      <Point>
        <X>375</X>
        <Y>293</Y>
      </Point>
      <Point>
        <X>377</X>
        <Y>292</Y>
      </Point>
      <Point>
        <X>379</X>
        <Y>292</Y>
      </Point>
      <Point>
        <X>382</X>
        <Y>292</Y>
      </Point>
      <Point>
        <X>384</X>
        <Y>292</Y>
      </Point>
      <Point>
        <X>386</X>
        <Y>292</Y>
      </Point>
      <Point>
        <X>388</X>
        <Y>291</Y>
      </Point>
      <Point>
        <X>390</X>
        <Y>291</Y>
      </Point>
      <Point>
        <X>391</X>
        <Y>291</Y>
      </Point>
      <Point>
        <X>393</X>
        <Y>291</Y>
      </Point>
      <Point>
        <X>394</X>
        <Y>291</Y>
      </Point>
      <Point>
        <X>394</X>
        <Y>292</Y>
      </Point>
    </SourcePath>
    <Output>0</Output>
    <RecognizedAs>-1</RecognizedAs>
  </Sequence>
</ArrayOfSequence>